psi_glad/__init__.py
psi_glad/utils.py
psi_glad/cv/__init__.py
psi_glad/cv/model.py
psi_glad/da/__init__.py
psi_glad/da/otda.py
psi_glad/gl/__init__.py
psi_glad/gl/base.py
psi_glad/gl/change_point_detector.py
psi_glad/gl/feature_selector.py
PSI_GLAD-0.1.1.dist-info/LICENSE
PSI_GLAD-0.1.1.dist-info/METADATA
PSI_GLAD-0.1.1.dist-info/WHEEL
PSI_GLAD-0.1.1.dist-info/top_level.txt
PSI_GLAD-0.1.1.dist-info/RECORD
