Metadata-Version: 2.1
Name: PSI-GLAD
Version: 0.1.1
Summary: A implementation of PSI-GLAD: Post-Selection Inference for Generalized Linear after Optimal Transport-based Domain Adaptation
Home-page: https://github.com/DAIR-Group/PSI-GLAD
Author: Nguyen Thang Loi
Author-email: 23520872@gm.uit.edu.vn
License: MIT
Classifier: License :: OSI Approved :: MIT License
Requires-Python: >=3.10
License-File: LICENSE
Requires-Dist: cvxpy
Requires-Dist: mpmath
Requires-Dist: numpy
Requires-Dist: POT
Requires-Dist: scikit-learn
Requires-Dist: scipy
